axon_programmer-0.0.8.dist-info/licenses/LICENSE.MD
src/__init__.py
src/gui.py
src/main.py
src/servo.py
axon_programmer-0.0.8.dist-info/METADATA
axon_programmer-0.0.8.dist-info/WHEEL
axon_programmer-0.0.8.dist-info/entry_points.txt
axon_programmer-0.0.8.dist-info/top_level.txt
axon_programmer-0.0.8.dist-info/RECORD
