Metadata-Version: 2.4
Name: axon-programmer
Version: 0.0.8
Summary: Cross-platform tool for detecting and programming Axon servos
Author: Pranav Yerramaneni
License: MIT
Classifier: Programming Language :: Python :: 3
Classifier: Operating System :: OS Independent
Requires-Python: >=3.6
License-File: LICENSE.MD
Requires-Dist: hidapi
Requires-Dist: PyQt6
Requires-Dist: PyQt6-Fluent-Widgets
Dynamic: author
Dynamic: classifier
Dynamic: description
Dynamic: description-content-type
Dynamic: license
Dynamic: license-file
Dynamic: requires-dist
Dynamic: requires-python
Dynamic: summary
